{"version":1,"resource":"vscode-remote://ssh-remote%2B192.168.99.10/home/vagrant/ansible_dir/index.html","entries":[{"id":"QCMo.html","timestamp":1672158909644},{"id":"2MC7.html","timestamp":1672240245241},{"id":"UooB.html","timestamp":1672328537484},{"id":"QJmI.html","timestamp":1672328782417},{"id":"mPVV.html","timestamp":1672395888607},{"id":"EbgS.html","timestamp":1675959126232},{"id":"zwc4.html","timestamp":1675959246787},{"id":"sptm.html","timestamp":1675960198181},{"id":"NnpP.html","timestamp":1675960519267}]}